Workbook

Sheet Summary
A1: BankAuction.co - Requirement Matrix vs Spec v1.0 (9 Oct 2026)
A2: Basis: repo main at 6404be2 + live audit of auction.bizsocio.com on 9 Oct 2026 (see 'Live audit 9 Oct' and 'Issues' tabs). 'Not verified' means not confirmed, not missing.
A4: Status | B4: All | C4: P0 Core | D4: P0 Comm | E4: P1 Intel | F4: P1 Partner | G4: P2 Pro | H4: P2 Scale
A5: Done | B5: =COUNTIF(Matrix!$E$2:$E$119,$A5) -> 17 | C5: =COUNTIFS(Matrix!$E$2:$E$119,$A5,Matrix!$C$2:$C$119,C$4) -> 16 | D5: =COUNTIFS(Matrix!$E$2:$E$119,$A5,Matrix!$C$2:$C$119,D$4) -> 0 | E5: =COUNTIFS(Matrix!$E$2:$E$119,$A5,Matrix!$C$2:$C$119,E$4) -> 1 | F5: =COUNTIFS(Matrix!$E$2:$E$119,$A5,Matrix!$C$2:$C$119,F$4) -> 0 | G5: =COUNTIFS(Matrix!$E$2:$E$119,$A5,Matrix!$C$2:$C$119,G$4) -> 0 | H5: =COUNTIFS(Matrix!$E$2:$E$119,$A5,Matrix!$C$2:$C$119,H$4) -> 0
A6: Partial | B6: =COUNTIF(Matrix!$E$2:$E$119,$A6) -> 38 | C6: =COUNTIFS(Matrix!$E$2:$E$119,$A6,Matrix!$C$2:$C$119,C$4) -> 27 | D6: =COUNTIFS(Matrix!$E$2:$E$119,$A6,Matrix!$C$2:$C$119,D$4) -> 6 | E6: =COUNTIFS(Matrix!$E$2:$E$119,$A6,Matrix!$C$2:$C$119,E$4) -> 5 | F6: =COUNTIFS(Matrix!$E$2:$E$119,$A6,Matrix!$C$2:$C$119,F$4) -> 0 | G6: =COUNTIFS(Matrix!$E$2:$E$119,$A6,Matrix!$C$2:$C$119,G$4) -> 0 | H6: =COUNTIFS(Matrix!$E$2:$E$119,$A6,Matrix!$C$2:$C$119,H$4) -> 0
A7: Not built | B7: =COUNTIF(Matrix!$E$2:$E$119,$A7) -> 47 | C7: =COUNTIFS(Matrix!$E$2:$E$119,$A7,Matrix!$C$2:$C$119,C$4) -> 19 | D7: =COUNTIFS(Matrix!$E$2:$E$119,$A7,Matrix!$C$2:$C$119,D$4) -> 14 | E7: =COUNTIFS(Matrix!$E$2:$E$119,$A7,Matrix!$C$2:$C$119,E$4) -> 5 | F7: =COUNTIFS(Matrix!$E$2:$E$119,$A7,Matrix!$C$2:$C$119,F$4) -> 5 | G7: =COUNTIFS(Matrix!$E$2:$E$119,$A7,Matrix!$C$2:$C$119,G$4) -> 3 | H7: =COUNTIFS(Matrix!$E$2:$E$119,$A7,Matrix!$C$2:$C$119,H$4) -> 1
A8: Not verified | B8: =COUNTIF(Matrix!$E$2:$E$119,$A8) -> 10 | C8: =COUNTIFS(Matrix!$E$2:$E$119,$A8,Matrix!$C$2:$C$119,C$4) -> 5 | D8: =COUNTIFS(Matrix!$E$2:$E$119,$A8,Matrix!$C$2:$C$119,D$4) -> 0 | E8: =COUNTIFS(Matrix!$E$2:$E$119,$A8,Matrix!$C$2:$C$119,E$4) -> 4 | F8: =COUNTIFS(Matrix!$E$2:$E$119,$A8,Matrix!$C$2:$C$119,F$4) -> 0 | G8: =COUNTIFS(Matrix!$E$2:$E$119,$A8,Matrix!$C$2:$C$119,G$4) -> 0 | H8: =COUNTIFS(Matrix!$E$2:$E$119,$A8,Matrix!$C$2:$C$119,H$4) -> 1
A9: Needs decision | B9: =COUNTIF(Matrix!$E$2:$E$119,$A9) -> 6 | C9: =COUNTIFS(Matrix!$E$2:$E$119,$A9,Matrix!$C$2:$C$119,C$4) -> 3 | D9: =COUNTIFS(Matrix!$E$2:$E$119,$A9,Matrix!$C$2:$C$119,D$4) -> 2 | E9: =COUNTIFS(Matrix!$E$2:$E$119,$A9,Matrix!$C$2:$C$119,E$4) -> 0 | F9: =COUNTIFS(Matrix!$E$2:$E$119,$A9,Matrix!$C$2:$C$119,F$4) -> 0 | G9: =COUNTIFS(Matrix!$E$2:$E$119,$A9,Matrix!$C$2:$C$119,G$4) -> 0 | H9: =COUNTIFS(Matrix!$E$2:$E$119,$A9,Matrix!$C$2:$C$119,H$4) -> 1
A10: Total | B10: =SUM(B5:B9) -> 118 | C10: =SUM(C5:C9) -> 70 | D10: =SUM(D5:D9) -> 22 | E10: =SUM(E5:E9) -> 15 | F10: =SUM(F5:F9) -> 5 | G10: =SUM(G5:G9) -> 3 | H10: =SUM(H5:H9) -> 3
A12: Headline reading
A13: - P0 trust & discovery: lifecycle, distinct counts, city parity are done, tested, deployed and live-verified.
A14: - Map is deployed but shows 0 pins in production because coordinates are missing. Clustering, 'search this area', detail-page map not built.
A15: - Search lacks sort, PIN and date filters. Cards lack share/compare/alert and freshness.
A16: - P0 commercial launch is largely not built: no entitlements, no checkout/webhook found, no alert delivery, no analytics, no audit log, no support tickets, no global security headers or rate limits.
A17: - Undated rounds currently count as ACTIVE; the spec says exclude them. Needs your confirmation before I change it.
A18: - CI and Vercel results for PRs #25/#26 were not read by me. Treat 'Tested' as local unit tests only.
A19: - 9 Oct live audit added 15 issues (4 P0). Biggest: city filter shows ~44% of catalogue (Nashik 8 vs 68), map 0 pins, /auctions pages capped at 48.
A20: Root-cause lead on missing cities: location is filled by an existing AI job (pipeline/geo.ts, enrichLocations, runs on the scheduler tick and after imports). ~5,200 rows still empty means the backlog is not draining or those rows were checked and returned no city. Phase 0 must establish which.
A21: Readiness by area (PM view)
A22: Area | D22: RAG | E22: Reason
A23: Core data correctness (lifecycle, counts) | D23: Amber | E23: Logic sound; location coverage ~44%; undated rule differs from spec
A24: Search and filters | D24: Amber | E24: Works; no sort/PIN/date; city filter hides ~56%; /auctions capped
A25: Map discovery | D25: Red | E25: Deployed but 0 pins; no clustering
A26: Property detail | D26: Amber | E26: Core fields good; no map/freshness/risk/share; similar-properties wrong
A27: Data sourcing and compliance | D27: Amber | E27: Guardrails + tests exist; source register/permissions undocumented
A28: Accounts and premium access | D28: Red | E28: No entitlements; pricing differs from spec
A29: Payments and billing | D29: Red | E29: Not live (site says so)
A30: Alerts | D30: Red | E30: Not live
A31: Partners / teams | D31: Red | E31: Not built
A32: SEO | D32: Amber | E32: Sitemap/robots/canonicals OK; 930 thin city URLs
A33: Security and privacy | D33: Amber | E33: Admin/API protected; no security headers/rate limits; borrower-data question
... A35: Launch readiness 20 Oct (paid) | D35: Red | E35: Commercial P0 not built

Sheet Phase plan
A1: Phase | B1: Goal | C1: Main work (see Matrix, filter 'Work phase') | D1: Exit gate - must be true before next phase | E1: Acceptance tests covered | F1: Owner approvals needed first | G1: Depends on | H1: Team roles | I1: Rough effort (working days, ESTIMATE) | J1: Biggest risk | K1: Open rows | L1: Done rows
A2: Phase 0 - Decide & baseline | B2: Remove ambiguity so the team stops guessing | C2: Decide: undated-round rule, canonical city names, state/city/locality rule, MMR list, plan prices+GST, free-tier masking, refund policy, borrower-data policy, map provider, media policy. Read-only baseline: how many published rows have geoCheckedAt empty vs checked-but-no-city; how many have coordinates, dates, category. Read admin Dashboard/Data Engine, CI and Vercel results for PRs #25/#26. Operator runs recon type-check on a machine with Prisma engines. | D2: Written decisions recorded in Owner decisions sheet; baseline numbers recorded; CI/Vercel results read; AI location provider status known | E2: None (unblocks all) | F2: All Phase 0 decisions (owner) | G2: None | H2: Owner + PM + 1 engineer (read-only) | I2: 2-3 | J2: Decisions slip; team builds on assumptions | K2: =COUNTIFS(Matrix!$O$2:$O$119,A2,Matrix!$E$2:$E$119,"<>Done") -> 4 | L2: =COUNTIFS(Matrix!$O$2:$O$119,A2,Matrix!$E$2:$E$119,"Done") -> 0
A3: Phase 1 - Trust fixes (code only) | B3: Make everything visitors can see honest and consistent. No production data writes. | C3: Pagination + true totals on /auctions/*; Auction Today view; similar-properties by area; 'N more listings mention <city>, not yet location-verified' link on city pages/search; merge city variants (Vasai/Vasai Virar, Aurangabad/Chhatrapati Sambhajinagar); undated rounds separated from active headline; ?keyword= alias; sort options + stable tiebreak; filter chips/clear-all; security headers + rate limits; thin city pages noindex or minimum-count rule; uncategorised/empty property types; investigate 'Pune' prefix; full disclaimer block. | D3: Every public count equals its results total; no page silently truncates; /auctions/* paginate; security headers present; tests added for each fix; each fix its own PR with CI green and preview reviewed | E3: AT-01, AT-03, AT-04, AT-07 (partly AT-02, AT-05, AT-18) | F3: Undated rule + canonical city names (Phase 0) | G3: Phase 0 | H3: 1-2 full-stack engineers + QA | I3: 5-8 | J3: Changing counts surprises stakeholders; explain before deploy | K3: =COUNTIFS(Matrix!$O$2:$O$119,A3,Matrix!$E$2:$E$119,"<>Done") -> 25 | L3: =COUNTIFS(Matrix!$O$2:$O$119,A3,Matrix!$E$2:$E$119,"Done") -> 0
A4: Phase 2 - Data foundation | B4: Fill the data the product depends on. Needs approval and rollback plan. | C4: Location: drain existing enrichLocations backlog (already scheduled; confirm why ~5,200 rows lack city), re-check rows that were checked but returned no city, review sample, report remaining unassigned. Coordinates: source reliable lat/long from source data or approved geocoder with precision flag; never guess. Category fill. Source register with terms/robots per source. Data-quality dashboard (missing city/coords/dates/prices, undated, end<start, duplicates). Run-state model (partial/no-change/stale). | D4: Unassigned-city share below agreed threshold (suggest <5%); coordinates present for agreed share with precision flag; before/after counts and rollback documented; dashboard live | E4: AT-05, AT-13, parts of AT-06 | F4: Written approval for each production data run + rollback plan; map provider; source permissions | G4: Phase 0 baseline | H4: 1 data engineer + 1 engineer + reviewer | I4: 8-15 (depends on AI provider and data quality) | J4: Bad AI geocodes; mitigation: sample review before bulk write, reversible log | K4: =COUNTIFS(Matrix!$O$2:$O$119,A4,Matrix!$E$2:$E$119,"<>Done") -> 12 | L4: =COUNTIFS(Matrix!$O$2:$O$119,A4,Matrix!$E$2:$E$119,"Done") -> 2
A5: Phase 3 - Discovery complete | B5: Finish P0 discovery to spec | C5: Map: clustering, search-this-area, loading/error states, split view, detail-page map; filters PIN/date/possession; cards: freshness, uncertainty label, save/share/compare/alert stubs; detail page: last-checked, source links, reserve history provenance, gallery rules, disclaimers; city pages: map/list, pagination; SEO audit; accessibility pass; coverage counters with as-of. | D5: Map shows real pins; map/list parity proven; detail page meets spec 4.7 core; accessibility + SEO checks pass | E5: AT-06, AT-07, AT-15 (part), AT-18, AT-20 (discovery half) | F5: Map provider/budget | G5: Phase 1, Phase 2 (coordinates) | H5: 2 engineers + designer + QA | I5: 12-18 | J5: Map traffic on free OSM tiles; check policy before launch | K5: =COUNTIFS(Matrix!$O$2:$O$119,A5,Matrix!$E$2:$E$119,"<>Done") -> 18 | L5: =COUNTIFS(Matrix!$O$2:$O$119,A5,Matrix!$E$2:$E$119,"Done") -> 3
A6: Phase 4 - Commercial launch | B6: Take money safely. Do not start without Phase 0 decisions. | C6: Plans/entitlements; sign-in recovery; consent records; checkout with server-side order, signed webhook, idempotency; GST invoices, refunds, credit notes; alert matching + delivery (email first) with dedupe/unsubscribe; analytics with consent; audit log; support tickets and correction path; backups/restore/RPO-RTO; incident process; premium field/document access enforced server-side and tested against direct URL and caching. | D6: Payment sandbox tests pass (single, duplicate, failed, refund, renewal); entitlement cannot be bypassed by URL or cache; alerts only to opted-in users; backup restore tested; owner signs release checklist | E6: AT-08, AT-09, AT-10, AT-11, AT-17, AT-19, AT-20 | F6: Prices, GST wording, refund policy, free-tier masking, gateway account and test keys, alert providers, borrower-data policy, CA review | G6: Phases 0-3 | H6: 2-3 engineers + QA + CA/legal input | I6: 25-40 | J6: Legal/CA sign-off delays; payment edge cases | K6: =COUNTIFS(Matrix!$O$2:$O$119,A6,Matrix!$E$2:$E$119,"<>Done") -> 23 | L6: =COUNTIFS(Matrix!$O$2:$O$119,A6,Matrix!$E$2:$E$119,"Done") -> 0
A7: Phase 5 - Intelligence | B7: Explain risk honestly and help buyers act | C7: Evidence-linked risk flags (descriptive, no score), reviewer workflow and corrections, compare, branded client report/share links, Auction of the Day, media rights model + gating. | D7: Every shown flag has evidence + review state; unknown never shown as clear; reports include timestamp, source links, missing-data markers | E7: AT-12, AT-15, AT-16 | F7: Risk rubric, legal service boundary, media policy | G7: Phase 3 | H7: 1-2 engineers + reviewer | I7: 15-25 | J7: Legal wording of risk copy | K7: =COUNTIFS(Matrix!$O$2:$O$119,A7,Matrix!$E$2:$E$119,"<>Done") -> 9 | L7: =COUNTIFS(Matrix!$O$2:$O$119,A7,Matrix!$E$2:$E$119,"Done") -> 1
A8: Phase 6 - Partner growth | B8: Grow through partners | C8: Partner onboarding, codes/links, 30-day attribution, commission engine with clawback, dashboard, statements. | D8: Attribution and payout totals reconcile on test data | E8: AT-14 | F8: One approved commission schedule + tax rules; agreements | G8: Phase 4 | H8: 1-2 engineers | I8: 15-25 | J8: Commission rules unsettled | K8: =COUNTIFS(Matrix!$O$2:$O$119,A8,Matrix!$E$2:$E$119,"<>Done") -> 5 | L8: =COUNTIFS(Matrix!$O$2:$O$119,A8,Matrix!$E$2:$E$119,"Done") -> 0
A9: Phase 7 - Pro suite & scale | B9: Professional suite and scale | C9: Team seats and pipeline, Private Desk workflows, language waves, new sources one by one with permission gates, load test. | D9: Each wave passes its own coverage/quality/permission gate | E9: AT-13, AT-17 (team parts) | F9: Team and Desk scope, languages, source permissions, load budget | G9: Phase 4-6 | H9: Per wave | I9: Ongoing | J9: Scope creep | K9: =COUNTIFS(Matrix!$O$2:$O$119,A9,Matrix!$E$2:$E$119,"<>Done") -> 5 | L9: =COUNTIFS(Matrix!$O$2:$O$119,A9,Matrix!$E$2:$E$119,"Done") -> 0
A11: Launch reality check (20 Oct 2026, 11 days away)
A12: - Phases 0 and 1 are realistic before 20 Oct if decisions arrive within 2 days. Phase 2 depends on the AI location provider and approvals.
A13: - Phases 3 and 4 are not realistic by 20 Oct. The spec says no paid subscriptions until payment, entitlement, refund and support paths pass.
A14: - Suggested option (owner decision): launch 20 Oct as a free discovery site with honest copy ('payments and alerts coming'), paid plans after the Phase 4 gate.
A15: - Effort numbers are rough planning estimates for the team to re-estimate, not commitments.
A16: - Rule for every phase: one focused PR per fix, CI green, preview reviewed, owner approval before merge/deploy, production smoke test after.

Sheet Issues
A1: ID | B1: Severity | C1: Area | D1: Finding | E1: Evidence | F1: Impact | G1: Recommended fix | H1: Needs your approval? | I1: Work phase
A2: I-01 | B2: P0 | C2: Search / Location | D2: City filter hides most listings: Nashik shows 8 but keyword search finds 68 (admin 64). City totals on /cities sum to ~4,068 of 9,304 published, so ~56% have no canonical city. | E2: Live: /properties?city=Nashik = 8 (5 active, 3 completed); ?q=nashik = 68; unmatched include Ozar, Sinnar, Eklahare, Deolali, Igatpuri, Malegaon and plain 'Nashik, 4220xx' addresses | F2: Visitors searching a city see a fraction of supply; homepage tiles understate. PR #25 followed your 'canonical city only' decision, which assumed few unassigned rows. | G2: 1) Show 'N more listings mention <city>, not yet location-verified' link on city pages and search (code only, reversible). 2) Approve a geoCity backfill run with review (data change - needs your written approval). 3) Admin bucket report. | H2: Yes (backfill) | I2: Phase 1 (link) + Phase 2 (backfill)
A3: I-02 | B3: P0 | C3: Map | D3: Map shows 0 pins on production. | E3: Live: all-properties, Mumbai, Bangalore, Pune, Chennai map views = 0 pins | F3: Map feature is invisible to users. Property.latitude/longitude essentially empty. | G3: Approve a coordinate-sourcing task from reliable data; do not geocode vaguely. Add clustering + detail map after. | H3: Yes | I3: Phase 2 (coordinates) + Phase 3 (clustering)
A4: I-03 | B4: P0 | C4: Search | D4: /auctions, /auctions/upcoming, /live, /completed capped at 48 with no pager; page 2 repeats page 1; label reads '48 auction(s)'. | E4: Live fetch of /auctions/upcoming?page=2 returned same first listing | F4: Most auctions unreachable via these pages; count misleading. Breaks AT-07. | G4: Add pagination + true total, or redirect these pages to /properties with status filter. | H4: No | I4: Phase 1 - Trust fixes (code only)
A5: I-04 | B5: P1 | C5: Lifecycle | D5: 'Active' = 6,988 of 9,304 (75%). Undated open rounds count as active; spec says exclude. | E5: Code: auctionLifecycle helper; live totals | F5: Headline opportunity numbers may be inflated. | G5: Count undated separately, exclude from headline. | H5: Confirm rule | I5: Phase 1 - Trust fixes (code only) (after Phase 0 rule)
A6: I-05 | B6: P1 | C6: Detail page | D6: 'Similar Properties' ignores location: a Nashik flat lists Bengaluru, Morbi, Surat. | E6: Live detail page text | F6: Looks broken, hurts trust. | G6: Filter by city/state and type. | H6: No | I6: Phase 1 - Trust fixes (code only)
A7: I-06 | B7: P1 | C7: Location data | D7: Duplicate/variant canonical cities (Vasai / Vasai Virar, Aurangabad / Chhatrapati Sambhajinagar); 972 city pages, 930 city URLs in sitemap. | E7: Live /cities, sitemap.xml | F7: Split counts, thin indexable pages. | G7: Merge variants; only index cities above a minimum count. | H7: Confirm names | I7: Phase 1 - Trust fixes (code only)
A8: I-07 | B8: P1 | C8: Commercial | D8: Pricing differs from spec (Rs 2,500/4,000/7,000 vs 1,499/2,699/4,999); Founding, Single, Team, Private Desk plans absent; payments and alerts 'not live'. | E8: Live /pricing | F8: Cannot take subscriptions on 20 Oct as specified. | G8: Owner approves prices, then build checkout/webhook/entitlements. | H8: Yes | I8: Phase 0 - Decide & baseline then Phase 4 - Commercial launch
A9: I-08 | B9: P1 | C9: Privacy | D9: Premium is sold on 'full borrower name & contact details'. | E9: Live /pricing and detail page | F9: Conflicts with spec section 13 data minimisation; legal exposure. | G9: Decide borrower-data policy before launch. | H9: Yes | I9: Phase 0 - Decide & baseline then Phase 1 - Trust fixes (code only)
A10: I-09 | B10: P1 | C10: Security | D10: Only HSTS header present. No CSP, X-Frame-Options, nosniff, Referrer-Policy. No rate limiting on public forms/login found. | E10: Live headers | F10: Standard hardening gap. | G10: Add headers in next.config + rate limits. | H10: No | I10: Phase 1 - Trust fixes (code only)
A11: I-10 | B11: P1 | C11: Detail page | D11: No map, no last-checked/source freshness, no risk flags, no save/share/compare/alert, thin disclaimer. | E11: Live detail page | F11: Misses most of spec 4.7. | G11: Build in order: freshness, map, share/save, disclaimer, then risk. | H11: No | I11: Phase 3 - Discovery complete
A12: I-11 | B12: P1 | C12: Commercial | D12: No analytics, no audit log, no support tickets, no consent records. | E12: Code scan | F12: Cannot measure funnel or run support. | G12: Build before paid launch. | H12: Yes (tool choice) | I12: Phase 4 - Commercial launch
... A16: I-15 | B16: P1 | C16: Verification gap | D16: Admin not audited (not logged in in my browser). CI/Vercel results for PRs #25/#26 unread. Sandbox cannot run build or 4 test files. | E16: Process | F16: Admin 64 vs public 68 differs by definition (admin includes drafts/removed) but is unverified. | G16: Give me a read-only admin login or screenshots of Dashboard/Data Engine; read CI. | H16: Yes | I16: Phase 0 - Decide & baseline

Sheet Live audit 9 Oct
A1: Page / check | B1: What was checked | C1: Expected | D1: Observed result
A2: Home / | B2: Loads, city tiles with active counts | C2: 8 tiles with counts | D2: PASS
A3: Home tile vs results | B3: Tile count == /properties?city&status=active | C3: Equal | D3: PASS (8/8, earlier check)
A4: /properties | B4: Total listings | C4: Total shown | D4: PASS - 9,304
A5: /properties?status=active | B5: Active total | C5: Shown | D5: 6,988 (suspect, I-04)
A6: /properties?status=completed | B6: Completed total | C6: Shown | D6: 2,356; active+completed = 9,344 > 9,304 (40 properties in both - allowed)
A7: /properties?city=Nashik | B7: City filter vs real supply | C7: ~68 | D7: FAIL - 8 (I-01)
A8: /properties?q=nashik | B8: Keyword search | C8: Matches | D8: 68 (works)
A9: /properties?keyword=nashik | B9: Alias param | C9: Filtered | D9: FAIL - returns 9,304 (I-13)
A10: /properties?state=Maharashtra | B10: State filter | C10: Filtered | D10: 1,713 (text fallback in use)
A11: /properties?view=map | B11: Pins | C11: Pins for geocoded rows | D11: FAIL - 0 pins (I-02)
A12: /cities | B12: City list | C12: Clean list | D12: 972 cities, variants (I-06)
... A32: Payments / alerts delivery | B32: Working | C32: Per spec | D32: NOT LIVE (stated on site)

Sheet Matrix
A1: Req ID | B1: Spec § | C1: Phase | D1: Requirement | E1: Status | F1: Evidence in code / live | G1: Gap / new work | H1: Tests | I1: Implemented | J1: Tested | K1: Merged | L1: Deployed | M1: Prod smoke-tested | N1: Owner decision | O1: Work phase
A2: LC-01 | B2: 3.2 | C2: P0 Core | D2: One central lifecycle rule for cards, detail, counts, filters, alerts, reports | E2: Done | F2: src/lib/domain/auctionLifecycle.ts (effectiveAuctionStatus, auctionStatusWhere, activeAuctionWhere); homepage, city, search use it | G2: Alerts/reports do not exist yet, so cannot confirm they will reuse it | H2: tests/auctionLifecycle.test.ts, resolveAuctionStatus.test.ts | I2: Yes | J2: Yes (unit, local) | K2: Yes | L2: Yes | M2: Partial (city tiles + counts checked live) | O2: Done - keep regression tests
A3: LC-02 | B3: 3.2 | C3: P0 Core | D3: States: Upcoming, Live, Auction Today, Completed, Cancelled, Postponed | E3: Done | F3: Helpers derive these at read time; IST day boundaries | G3: None known | H3: auctionLifecycle.test.ts (boundary cases) | I3: Yes | J3: Yes (unit, local) | K3: Yes | L3: Yes | M3: Not verified | N3: Approve 'Auction Today' rule wording | O3: Done - keep regression tests
A4: LC-03 | B4: 3.2 | C4: P0 Core | D4: Undated/Needs Review state; undated rounds excluded from trusted active headline and reported separately | E4: Not built | F4: Helper treats undated open rounds as never over, so they count as ACTIVE today | G4: Add Undated state, exclude from active headline, add count in admin data-quality view | H4: None | I4: No | J4: No | K4: No | L4: No | M4: No | N4: Confirm: spec wins over current behaviour | O4: Phase 1 - Trust fixes (code only)
A5: LC-04 | B5: 3.2 | C5: P0 Core | D5: Flag end-before-start and partial-date records for review; never auto-repair | E5: Not verified | F5: src/lib/pipeline/completeness.ts exists; not checked against this rule | G5: Check rule coverage + surface in admin | H5: tests/completeness.test.ts (scope not checked) | I5: Not verified | J5: Not verified | K5: Yes | L5: Yes | M5: No | O5: Phase 1 - Trust fixes (code only)
A6: LC-05 | B6: 3.2 | C6: P0 Core | D6: Never overwrite source facts to fix status; status derived at read time | E6: Done | F6: Derived in code; raw values kept (fieldProvenance.ts, PropertyChange) | G6: None known | H6: provenance.test.ts | I6: Yes | J6: Yes (unit, local) | K6: Yes | L6: Yes | M6: Not verified | O6: Done - keep regression tests
A7: CT-01 | B7: 3.3 | C7: P0 Core | D7: Count distinct properties, not round rows (AT-03) | E7: Done | F7: cityCounts.ts + cities.ts groupBy on property rows; property-level where in publishedWhere | G7: Other counters (admin, stats) not audited | H7: tests/cityCounts.test.ts (13) | I7: Yes | J7: Yes (unit, local) | K7: Yes | L7: Yes | M7: Yes (live tiles = results) | O7: Done - keep regression tests
A8: CT-02 | B8: 3.3 | C8: P0 Core | D8: Catalogue total includes round-less published properties; active excludes them (AT-04) | E8: Done | F8: cities.ts 'total' vs active count; activeAuctionWhere requires a round | G8: None known | H8: cityCounts.test.ts | I8: Yes | J8: Yes (unit, local) | K8: Yes | L8: Yes | M8: Partial | O8: Done - keep regression tests
A9: CT-03 | B9: 3.3 | C9: P0 Core | D9: Cancelled/Postponed excluded from active and reported separately | E9: Partial | F9: Excluded from active via lifecycle helper | G9: No separate report/count anywhere | H9: auctionLifecycle.test.ts (exclusion only) | I9: Partial | J9: Partial | K9: Yes | L9: Yes | M9: No | O9: Phase 1 - Trust fixes (code only)
A10: CT-04 | B10: 3.3 | C10: P0 Core | D10: Homepage city counts use canonical city only; missing city is a separate bucket (AT-05) | E10: Partial | F10: Live: city totals on /cities sum to ~4,068 of 9,304 published, so ~5,236 (56%) have no usable canonical city. Nashik: 8 by city, 68 by keyword | G10: Bucket is invisible to visitors and admin. Needs report + location backfill | H10: cityCounts.test.ts | I10: Yes | J10: Yes (unit, local) | K10: Yes | L10: Yes | M10: FAIL (visitor-visible gap, see I-01) | N10: Approve geoCity backfill | O10: Phase 1 - Trust fixes (code only)
A11: CT-05 | B11: 3.3 | C11: P0 Core | D11: City card count == results total (AT-01) | E11: Done | F11: Both use publishedWhere. Parity holds, but both exclude listings without canonical city, so the parity is on an incomplete set | G11: None | H11: cityCounts.test.ts + live check of all 8 tiles | I11: Yes | J11: Yes (unit + live) | K11: Yes | L11: Yes | M11: Yes (parity) / FAIL (coverage) | O11: Done - keep regression tests
A12: DM-01 | B12: 3.1 | C12: P0 Core | D12: Property: coords AND coordinate precision | E12: Partial | F12: Property.latitude/longitude, geoCity/State/Locality, geoCheckedAt | G12: No precision field; production coordinates are effectively empty (live map = 0 pins) | H12: propertyMap.test.ts (validation only) | I12: Partial | J12: Partial | K12: Yes | L12: Yes | M12: Yes - confirmed gap | N12: Approve data task to source coordinates | O12: Phase 2 - Data foundation
A13: DM-02 | B13: 3.1 | C13: P0 Core | D13: Auction round fields (EMD, increment, inspection, possession, notice, type, dates) | E13: Done | F13: Auction model: emd, minimumIncrement, inspection*, possessionStatus, noticeNumber, auctionType, externalAuctionId | G13: Timezone stored implicitly (IST in logic); possession is free text not typed | H13: None specific | I13: Yes | J13: No | K13: Yes | L13: Yes | M13: Not verified | O13: Phase 3 - Discovery complete
A14: DM-03 | B14: 3.1 | C14: P0 Core | D14: Institution/source register with terms review, robots state, coverage, last checked | E14: Partial | F14: Bank, Source, FeedSource, SourceRunLog; admin sources/feeds pages; robotsGate | G14: No explicit terms-review / permission record per source | H14: sourceCompliance.test.ts, robotsRules.test.ts | I14: Partial | J14: Partial | K14: Yes | L14: Yes | M14: Not verified | N14: Approve source register | O14: Phase 2 - Data foundation
A15: DM-04 | B15: 3.1 | C15: P0 Core | D15: Evidence/provenance per field with reviewer + correction history | E15: Partial | F15: fieldProvenance.ts, fieldObservations.ts, PropertyChange, mergeLog | G15: No reviewer identity/correction workflow; not shown to users | H15: provenance.test.ts | I15: Partial | J15: Partial | K15: Yes | L15: Yes | M15: No | O15: Phase 2 - Data foundation
A16: DM-05 | B16: 3.1 | C16: P1 Intel | D16: Media/document with permission status, review state | E16: Not verified | F16: Media, Document, MediaAsset, SourceMedia models | G16: Permission/rights fields not confirmed | H16: None | I16: Not verified | J16: No | K16: Yes | L16: Yes | M16: No | N16: Media policy decision | O16: Phase 5 - Intelligence
A17: DM-06 | B17: 3.1 | C17: P0 Comm | D17: User/subscription: plan, entitlement dates, provider IDs, invoices, audit | E17: Not built | F17: User and Payment only | G17: No Subscription/Entitlement/Invoice models | H17: None | I17: No | J17: No | K17: No | L17: No | M17: No | N17: Prices + plans | O17: Phase 4 - Commercial launch
A18: DM-07 | B18: 3.1 | C18: P0 Comm | D18: Saved search/alert with channels, frequency, consent, pause, delivery result | E18: Partial | F18: SavedSearch, Alert (type, filters, active) | G18: No channel, frequency, consent, pause or delivery log | H18: None | I18: Partial | J18: No | K18: Yes | L18: Yes | M18: Not verified | O18: Phase 4 - Commercial launch
A19: DM-08 | B19: 3.1 | C19: P1 Partner | D19: Partner/referral entities | E19: Not built | F19: Absent | G19: Full schema | H19: None | I19: No | J19: No | K19: No | L19: No | M19: No | N19: Commission rulebook | O19: Phase 6 - Partner growth
A20: DM-09 | B20: 3.1 | C20: P2 Pro | D20: Team/deal entities | E20: Not built | F20: Absent | G20: Full schema | H20: None | I20: No | J20: No | K20: No | L20: No | M20: No | N20: Team/Private Desk scope | O20: Phase 7 - Pro suite & scale
A21: NAV-01 | B21: 4.1 | C21: P0 Core | D21: Main nav incl. Search, Map View, Cities, Banks, Calendar, How it works, Pricing, Partners, Guides, Help, Sign in | E21: Partial | F21: Pages: properties, cities, banks, how-it-works, pricing, blog, contact, login, register | G21: No auction calendar, no partner page; Map is a toggle, not a nav entry | H21: None | I21: Partial | J21: No | K21: Yes | L21: Yes | M21: Not verified | O21: Phase 3 - Discovery complete
A22: HP-01 | B22: 4.2 | C22: P0 Core | D22: Hero + search by keyword/location/PIN with filters | E22: Partial | F22: Home page search exists | G22: PIN-code search not present; filter set not checked | H22: None | I22: Partial | J22: No | K22: Yes | L22: Yes | M22: Not verified | O22: Phase 3 - Discovery complete
A23: HP-02 | B23: 4.2 | C23: P0 Core | D23: Coverage counters with 'as of' timestamp from defined metrics | E23: Not built | F23: Stat block hidden. Live home shows city tiles with active counts only | G23: Define metrics, show as-of, re-enable | H23: None | I23: No | J23: No | K23: No | L23: No | M23: Confirmed missing | O23: Phase 1 - Trust fixes (code only)
A24: HP-03 | B24: 4.2 | C24: P0 Core | D24: Active city tiles = qualifying properties; link to same-count page | E24: Done | F24: page.tsx tiles -> /properties?city=X&status=active | G24: None | H24: cityCounts.test.ts | I24: Yes | J24: Yes | K24: Yes | L24: Yes | M24: Yes | O24: Phase 3 - Discovery complete
A25: HP-04 | B25: 4.2 | C25: P1 Intel | D25: Auction of the Day, recent additions, map discovery, guides, video, pricing sections | E25: Partial | F25: Recent/blog/pricing exist | G25: Auction of the Day not found; map section not on home | H25: None | I25: Partial | J25: No | K25: Yes | L25: Yes | M25: Not verified | O25: Phase 3 - Discovery complete
A26: HP-05 | B26: 4.2 | C26: P0 Core | D26: No 'verified title' / 'guaranteed' claims | E26: Done | F26: Claims guard test | G26: None known | H26: tests/publicClaims.test.ts | I26: Yes | J26: Yes (unit) | K26: Yes | L26: Yes | M26: Not verified | O26: Done - keep regression tests
A27: SR-01 | B27: 4.3 | C27: P0 Core | D27: Filters: keyword, city, state, locality, bank, type, price, status | E27: Done | F27: publishedWhere.ts + PropertyFilterForm | G27: None | H27: cityCounts.test.ts, propertyMap.test.ts (filter parity) | I27: Yes | J27: Yes (unit) | K27: Yes | L27: Yes | M27: Not verified | O27: Done - keep regression tests
A28: SR-02 | B28: 4.3 | C28: P0 Core | D28: Filters: PIN code, auction date range, possession type | E28: Not built | F28: Absent | G28: Add filters + schema/index check | H28: None | I28: No | J28: No | K28: No | L28: No | M28: No | O28: Phase 3 - Discovery complete
A29: SR-03 | B29: 4.3 | C29: P0 Core | D29: Sort: newest, deadline, price low/high, relevance; deterministic | E29: Not built | F29: Fixed createdAt desc only; no tiebreaker | G29: Add sort + id tiebreak + URL param | H29: None | I29: No | J29: No | K29: No | L29: No | M29: No | O29: Phase 1 - Trust fixes (code only)
A30: SR-04 | B30: 4.3 | C30: P0 Core | D30: Shareable URLs; clear-all and active-filter chips | E30: Partial | F30: Filters in URL. Param names: city, state, locality, q (keyword). Note keyword param ?keyword= is ignored (returns all 9,304) | G30: Chips and clear-all not confirmed | H30: None | I30: Partial | J30: No | K30: Yes | L30: Yes | M30: Partial | O30: Phase 1 - Trust fixes (code only)
A31: SR-05 | B31: 4.3 | C31: P0 Core | D31: Count, applied filters, pagination, empty state, reset suggestions | E31: Partial | F31: Count + pagination exist | G31: Reset suggestions not confirmed | H31: propertyMap.test.ts (page params) | I31: Partial | J31: Partial | K31: Yes | L31: Yes | M31: Not verified | O31: Phase 1 - Trust fixes (code only)
A32: SR-06 | B32: 4.3 | C32: P0 Core | D32: No silent broadening of location/text matching | E32: Partial | F32: City: canonical only. Live proof: Nashik city filter 8 vs keyword 68. State/locality still use text fallback, so the three filters disagree | G32: Make state, city and locality rules consistent; surface unverified matches instead of hiding them | H32: cityCounts.test.ts | I32: Partial | J32: Partial | K32: Yes | L32: Yes | M32: FAIL (I-01) | N32: Decide on state/locality fallback | O32: Phase 1 - Trust fixes (code only)
A33: CD-01 | B33: 4.4 | C33: P0 Core | D33: Card fields: title, location (+uncertainty label), price, date, institution, status, freshness, thumbnail, risk | E33: Partial | F33: PropertyCard shows most via toPropertyCardData | G33: No freshness, no uncertainty label, no risk indicator | H33: None | I33: Partial | J33: No | K33: Yes | L33: Yes | M33: Not verified | O33: Phase 3 - Discovery complete
A34: CD-02 | B34: 4.4 | C34: P0 Core | D34: Card actions: save, share, compare, alert (gated) | E34: Partial | F34: Save exists (SavedProperty) | G34: Share/compare/alert missing | H34: None | I34: Partial | J34: No | K34: Yes | L34: Yes | M34: Not verified | O34: Phase 3 - Discovery complete
A35: CD-03 | B35: 4.4 | C35: P0 Core | D35: 'Not available in source' labels; placeholder unless media cleared | E35: Not verified | F35: Not checked | G35: Check card + detail | H35: None | I35: Not verified | J35: No | K35: Yes | L35: Yes | M35: No | N35: Media policy | O35: Phase 1 - Trust fixes (code only)
A36: MP-01 | B36: 4.5 | C36: P0 Core | D36: Map/list toggle | E36: Done | F36: ViewToggle.tsx, properties/page.tsx ?view=map | G36: None | H36: propertyMap.test.ts (15) | I36: Yes | J36: Yes (unit, local) | K36: Yes | L36: Yes | M36: Partial (toggle works) | O36: Done - keep regression tests
A37: MP-02 | B37: 4.5 | C37: P0 Core | D37: Plot only usable coordinates; no false geocoding | E37: Done | F37: coordinates.ts (India bounds, finite, not 0,0) | G37: None | H37: propertyMap.test.ts | I37: Yes | J37: Yes (unit) | K37: Yes | L37: Yes | M37: Yes (nothing invented) | O37: Done - keep regression tests
A38: MP-03 | B38: 4.5 | C38: P0 Core | D38: Pins show real data on production | E38: Not built | F38: Live: 0 pins on all-properties, Mumbai, Bangalore, Pune, Chennai | G38: Coordinates missing in production data | H38: N/A | I38: Yes | J38: Yes (unit) | K38: Yes | L38: Yes | M38: FAIL (0 pins) | N38: Approve coordinate sourcing task | O38: Phase 2 - Data foundation
A39: MP-04 | B39: 4.5 | C39: P0 Core | D39: Pin summary links to detail; pin<->card selection | E39: Done | F39: PropertyMapView.tsx reducer, text-node popups | G39: Never exercised on real pins in production | H39: propertyMap.test.ts (reducer) | I39: Yes | J39: Yes (unit) | K39: Yes | L39: Yes | M39: NOT VERIFIED (no pins) | O39: Done - keep regression tests
A40: MP-05 | B40: 4.5 | C40: P0 Core | D40: Clustering at zoomed-out levels (required) | E40: Not built | F40: No cluster library | G40: Add clustering | H40: None | I40: No | J40: No | K40: No | L40: No | M40: No | O40: Phase 3 - Discovery complete
A41: MP-06 | B41: 4.5 | C41: P0 Core | D41: Desktop split view; mobile map screen with list toggle | E41: Partial | F41: Map + card list; responsive | G41: True split view not confirmed | H41: None | I41: Partial | J41: No | K41: Yes | L41: Yes | M41: Not verified | O41: Phase 3 - Discovery complete
A42: MP-07 | B42: 4.5 | C42: P0 Core | D42: 'Search this area' action | E42: Not built | F42: Absent | G42: Add bounds query | H42: None | I42: No | J42: No | K42: No | L42: No | M42: No | O42: Phase 3 - Discovery complete
A43: MP-08 | B43: 4.5 | C43: P0 Core | D43: Loading, no-results, no-coordinate, provider-error states | E43: Partial | F43: No-coordinate message seen live; list empty state | G43: Loading + tile/provider error states not confirmed | H43: None | I43: Partial | J43: No | K43: Yes | L43: Yes | M43: Partial | O43: Phase 3 - Discovery complete
A44: MP-09 | B44: 4.5 | C44: P0 Core | D44: Approved provider, costs, attribution | E44: Needs decision | F44: Leaflet + OpenStreetMap tiles, no key | G44: OSM tile policy is not for heavy commercial traffic; needs a decision | H44: None | I44: Yes | J44: n/a | K44: Yes | L44: Yes | M44: n/a | N44: Approve provider/budget | O44: Phase 0 - Decide & baseline
A45: CY-01 | B45: 4.6 | C45: P0 Core | D45: Mumbai city vs MMR as separate views | E45: Needs decision | F45: Only city view exists | G45: MMR list is a draft; do not code until validated | H45: None | I45: No | J45: No | K45: No | L45: No | M45: No | N45: Validate MMR list | O45: Phase 0 - Decide & baseline
A46: CY-02 | B46: 4.6 | C46: P0 Core | D46: City page: active count, catalogue count, labels, filters, pagination | E46: Partial | F46: city/[slug]: active list capped at 48 with 'See all' link. Live /cities lists 972 cities | G46: Page size 48 with 'See all N' link instead of real pagination; no filters | H46: cityCounts.test.ts (counts) | I46: Partial | J46: Partial | K46: Yes | L46: Yes | M46: Partial | O46: Phase 1 - Trust fixes (code only)
A47: CY-03 | B47: 4.6 | C47: P0 Core | D47: City page map/list discovery | E47: Not built | F47: Absent on city pages | G47: Reuse map toggle | H47: None | I47: No | J47: No | K47: No | L47: No | M47: No | O47: Phase 3 - Discovery complete
A48: CY-04 | B48: 4.6 | C48: P0 Core | D48: Unassigned/unknown location totals reported | E48: Not built | F48: Computed in cities.ts but never displayed. Live gap ~56% of catalogue | G48: Show 'N more listings mention <city>, not yet location-verified' and an admin bucket report | H48: cityCounts.test.ts | I48: Partial | J48: Yes (unit) | K48: Yes | L48: Yes | M48: FAIL | N48: Approve geoCity backfill | O48: Phase 1 - Trust fixes (code only)
A49: CY-05 | B49: 4.6 | C49: P2 Scale | D49: Useful unique SEO city/institution pages, no thin pages | E49: Not verified | F49: City, bank pages exist | G49: Not audited for thin/duplicate content | H49: None | I49: Not verified | J49: No | K49: Yes | L49: Yes | M49: No | O49: Phase 3 - Discovery complete
A50: DT-01 | B50: 4.7 | C50: P0 Core | D50: Detail: reserve, dates, EMD, increment, institution, type, possession, inspection | E50: Done | F50: property/[slug]/page.tsx fields | G50: Eligibility/process notes not confirmed | H50: None | I50: Yes | J50: No | K50: Yes | L50: Yes | M50: Not verified | O50: Phase 3 - Discovery complete
A51: DT-02 | B51: 4.7 | C51: P1 Intel | D51: Prior rounds with status/date/reserve history; provenance per value | E51: Partial | F51: Prior rounds table (reserve, EMD, dates, status) | G51: No per-value provenance or reserve-history chart | H51: None | I51: Partial | J51: No | K51: Yes | L51: Yes | M51: Not verified | O51: Phase 3 - Discovery complete
A52: DT-03 | B52: 4.7 | C52: P0 Core | D52: Source notice link + last-checked timestamp | E52: Not built | F52: Live detail page (flat-jail-road-nashik): no last-checked or source-freshness line | G52: Add last-checked + source link | H52: lastSeen.test.ts (pipeline only) | I52: Not verified | J52: No | K52: Yes | L52: Yes | M52: Confirmed missing | O52: Phase 3 - Discovery complete
A53: DT-04 | B53: 4.7 | C53: P0 Core | D53: Detail map when coordinates reliable | E53: Not built | F53: Live detail page has no map | G53: Reuse coordinates.ts + map component | H53: None | I53: No | J53: No | K53: No | L53: No | M53: Confirmed missing | O53: Phase 3 - Discovery complete
A54: DT-05 | B54: 4.7 | C54: P1 Intel | D54: Gallery of permitted media with placeholder | E54: Not verified | F54: Media models exist | G54: Rights gating not confirmed | H54: None | I54: Not verified | J54: No | K54: Yes | L54: Yes | M54: No | N54: Media policy | O54: Phase 3 - Discovery complete
A55: DT-06 | B55: 4.7 | C55: P1 Intel | D55: Risk indicators with evidence, confidence, review date | E55: Not built | F55: No risk model or UI | G55: Build per section 5 | H55: None | I55: No | J55: No | K55: No | L55: No | M55: No | N55: Risk rubric | O55: Phase 5 - Intelligence
A56: DT-07 | B56: 4.7 | C56: P1 Intel | D56: Share, compare, alert, client card, request professional help | E56: Partial | F56: Live detail: WhatsApp enquiry + Contact Us only. No save/share/compare/alert/client card | G56: Others absent | H56: None | I56: Partial | J56: No | K56: Yes | L56: Yes | M56: Confirmed | N56: Legal service boundary | O56: Phase 3 - Discovery complete
A57: DT-08 | B57: 4.7 | C57: P0 Core | D57: Research-only disclaimer on detail | E57: Partial | F57: Live detail page has one line 'Always confirm auction details against the official documents'. No full disclaimer block | G57: Detail-page disclaimer not confirmed | H57: publicClaims.test.ts | I57: Partial | J57: Partial | K57: Yes | L57: Yes | M57: Partial | O57: Phase 1 - Trust fixes (code only)
A58: CM-01 | B58: 4.8 | C58: P1 Intel | D58: Compare selected properties | E58: Not built | F58: Absent | G58: Build compare UI + URL | H58: None | I58: No | J58: No | K58: No | L58: No | M58: No | O58: Phase 5 - Intelligence
A59: CM-02 | B59: 4.8 | C59: P1 Intel | D59: Branded client card/report with timestamp, source links, missing-data flags (AT-15) | E59: Not built | F59: Absent | G59: Build report generator | H59: None | I59: No | J59: No | K59: No | L59: No | M59: No | O59: Phase 5 - Intelligence
A60: CM-03 | B60: 4.8 | C60: P1 Intel | D60: Revocable/expiring public share links; private notes separation | E60: Not built | F60: Absent | G60: Share-token model | H60: None | I60: No | J60: No | K60: No | L60: No | M60: No | O60: Phase 5 - Intelligence
A61: RK-01 | B61: 5.1 | C61: P1 Intel | D61: Risk fields: possession, litigation, dues, tenancy, title concerns, doc completeness, confidence | E61: Partial | F61: possessionStatus (free text), completeness.ts | G61: Others absent; not evidence-linked | H61: completeness.test.ts | I61: Partial | J61: Partial | K61: Yes | L61: Yes | M61: No | N61: Risk rubric | O61: Phase 5 - Intelligence
A62: RK-02 | B62: 5.2 | C62: P1 Intel | D62: No opaque legal score; descriptive evidence-backed flags | E62: Done | F62: No score exists | G62: Keep it that way until rubric approved | H62: N/A | I62: Yes | J62: n/a | K62: Yes | L62: Yes | M62: n/a | N62: Rubric | O62: Phase 5 - Intelligence
A63: RK-03 | B63: 5.3 | C63: P1 Intel | D63: Reviewer workflow: confirmed/source-stated/uncertain/incorrect/legal review; correction history | E63: Not built | F63: pipeline/review.ts is for duplicates/locations, not risk | G63: Build review states + audit trail | H63: None | I63: No | J63: No | K63: No | L63: No | M63: No | O63: Phase 5 - Intelligence
A64: RK-04 | B64: 5.3 | C64: P0 Comm | D64: Public correction/contact path, 24h review SLA (AT-19) | E64: Partial | F64: Contact page + Lead model | G64: No property-linked 'report error', no status/SLA tracking | H64: None | I64: Partial | J64: No | K64: Yes | L64: Yes | M64: Not verified | N64: Staffing SLA | O64: Phase 4 - Commercial launch
A65: SC-01 | B65: 6 | C65: P0 Core | D65: Source register: terms, robots, last success, health, limitations | E65: Partial | F65: Source, FeedSource, SourceRunLog, admin pages | G65: Terms-review record missing | H65: sourceCompliance.test.ts | I65: Partial | J65: Partial | K65: Yes | L65: Yes | M65: Not verified | N65: Approve source register | O65: Phase 2 - Data foundation
A66: SC-02 | B66: 6 | C66: P0 Core | D66: Never bypass robots/401/403/CAPTCHA; stop and record refusal (AT-13) | E66: Done | F66: robotsGate.ts, sourceProtection.ts, httpStatus handling | G66: Not re-audited per source this session | H66: robotsRules.test.ts, httpStatus.test.ts, sourceProtection.test.ts | I66: Yes | J66: Unit tests exist | K66: Yes | L66: Yes | M66: Not verified | O66: Phase 2 - Data foundation
A67: SC-03 | B67: 6 | C67: P0 Core | D67: Store source URL, ID, retrieval time, extraction version, field evidence | E67: Partial | F67: externalAuctionId, noticeNumber, fieldProvenance | G67: Extraction version not confirmed | H67: provenance.test.ts | I67: Partial | J67: Partial | K67: Yes | L67: Yes | M67: No | O67: Phase 2 - Data foundation
A68: SC-04 | B68: 6 | C68: P0 Core | D68: Conservative dedupe; ambiguous -> review | E68: Done | F68: deduplication/, pipeline/duplicates.ts, admin duplicates page | G68: None known | H68: dedupe.test.ts | I68: Yes | J68: Yes (unit) | K68: Yes | L68: Yes | M68: Not verified | O68: Phase 2 - Data foundation
A69: SC-05 | B69: 6 | C69: P0 Core | D69: Run states: success/no-change/blocked/partial/failed/stale distinct | E69: Partial | F69: SourceRunLog status: ok/error/skipped/blocked; schedulerHealth | G69: No partial, no-change or stale state | H69: scheduler.test.ts, zeroYield.test.ts | I69: Partial | J69: Partial | K69: Yes | L69: Yes | M69: Not verified | O69: Phase 2 - Data foundation
A70: SC-06 | B70: 6 | C70: P0 Core | D70: Do not ingest findauction.in | E70: Not verified | F70: Not checked in registry this session | G70: Check src/data-sources/registry.ts | H70: sourceClassification.test.ts (scope not checked) | I70: Not verified | J70: No | K70: Yes | L70: Yes | M70: No | O70: Phase 2 - Data foundation
A71: SC-07 | B71: 6 | C71: P1 Intel | D71: No media ingest without type + permission | E71: Not verified | F71: Not checked | G71: Audit media pipeline | H71: None | I71: Not verified | J71: No | K71: Yes | L71: Yes | M71: No | N71: Media policy | O71: Phase 2 - Data foundation
A72: AC-01 | B72: 7.1 | C72: P0 Comm | D72: Email/phone sign-in, recovery, preferences | E72: Partial | F72: login/register, userSession.ts, password.ts | G72: No phone/OTP, no recovery flow found | H72: None | I72: Partial | J72: No | K72: Yes | L72: Yes | M72: Not verified | O72: Phase 4 - Commercial launch
A73: AC-02 | B73: 7.1 | C73: P0 Comm | D73: Explicit opt-in per channel; simple opt-out; consent log | E73: Not built | F73: Absent | G73: Consent model + UI | H73: None | I73: No | J73: No | K73: No | L73: No | M73: No | O73: Phase 4 - Commercial launch
A74: AC-03 | B74: 7.1 | C74: P0 Comm | D74: Saved properties, searches, alert history, invoices, support requests | E74: Partial | F74: saved-properties, my-alerts pages | G74: No invoices, alert history or tickets | H74: None | I74: Partial | J74: No | K74: Yes | L74: Yes | M74: Not verified | O74: Phase 4 - Commercial launch
A75: AC-04 | B75: 7.1 | C75: P0 Comm | D75: Server-side authorisation of premium fields/docs/APIs; cache leakage tests (AT-08) | E75: Not built | F75: No tiers or entitlements; public API keys exist (ApiKey) | G75: Entitlement layer + tests | H75: borrowerExposure.test.ts (different issue) | I75: No | J75: No | K75: No | L75: No | M75: No | N75: Free-tier masking decision | O75: Phase 4 - Commercial launch
A76: TR-01 | B76: 7.2 | C76: P0 Comm | D76: Tiers: visitor, free, single notice, quarterly/half/yearly, Founding, Team, Private Desk | E76: Not built | F76: Pricing page only | G76: Plans, entitlements, masking | H76: None | I76: No | J76: No | K76: Yes | L76: Yes | M76: Not verified | N76: Approve plans | O76: Phase 4 - Commercial launch
A77: TR-02 | B77: 7.3 | C77: P0 Comm | D77: Approved prices, GST wording, no contradictory prices | E77: Needs decision | F77: Live /pricing: 3 Month Rs 2,500, 6 Month Rs 4,000, 1 Year Rs 7,000, GST included. Spec proposals: 1,499 / 2,699 / 4,999 plus Founding, Single, Team, Desk | G77: Prices differ from spec; no Founding/Single/Team/Desk plans listed | H77: None | I77: No | J77: No | K77: No | L77: No | M77: Yes (page loads, copy honest: payments not live) | N77: Approve prices + GST wording | O77: Phase 0 - Decide & baseline
A78: PY-01 | B78: 7.4 | C78: P0 Comm | D78: Gateway checkout; server-side order; signed webhook; idempotency (AT-09) | E78: Partial | F78: Live /pricing says 'Online payment isn't live yet - contact us to activate a plan manually'. No webhook route in code | G78: No webhook route or checkout flow found under src/app/api | H78: None | I78: Partial | J78: No | K78: Yes | L78: Yes | M78: Confirmed not live | N78: Gateway account + test keys | O78: Phase 4 - Commercial launch
A79: PY-02 | B79: 7.4 | C79: P0 Comm | D79: Entitlement only after verified payment | E79: Not built | F79: No entitlements | G79: Build with PY-01 | H79: None | I79: No | J79: No | K79: No | L79: No | M79: No | O79: Phase 4 - Commercial launch
A80: PY-03 | B80: 7.4 | C80: P0 Comm | D80: Recurring (UPI AutoPay/card) with mandate consent | E80: Needs decision | F80: Absent | G80: Only if approved | H80: None | I80: No | J80: No | K80: No | L80: No | M80: No | N80: Approve or drop | O80: Phase 4 - Commercial launch
A81: PY-04 | B81: 7.4 | C81: P0 Comm | D81: GST invoices, credit notes, numbering | E81: Not built | F81: Absent | G81: CA-approved rules first | H81: None | I81: No | J81: No | K81: No | L81: No | M81: No | N81: CA input | O81: Phase 4 - Commercial launch
A82: PY-05 | B82: 7.4 | C82: P0 Comm | D82: Refund policy shown pre-payment; refund/cancel/renew/expiry flows (AT-10) | E82: Not built | F82: Payment.status has 'refunded' only | G82: Policy + flows | H82: None | I82: No | J82: No | K82: No | L82: No | M82: No | N82: Approve refund policy | O82: Phase 4 - Commercial launch
A83: AL-01 | B83: 8 | C83: P0 Comm | D83: Alerts by city/PIN/bank/budget/type/status | E83: Partial | F83: Alert.filters JSON, my-alerts | G83: PIN absent; matching engine not found | H83: None | I83: Partial | J83: No | K83: Yes | L83: Yes | M83: Not verified | O83: Phase 4 - Commercial launch
A84: AL-02 | B84: 8 | C84: P0 Comm | D84: Delivery: email, WhatsApp, push; immediate + digest (AT-11) | E84: Not built | F84: Live /pricing says personalised alerts 'planned and not yet available'. No provider code | G84: Choose providers, templates, jobs | H84: None | I84: No | J84: No | K84: No | L84: No | M84: Confirmed not live | N84: Providers + cost | O84: Phase 4 - Commercial launch
A85: AL-03 | B85: 8 | C85: P0 Comm | D85: Dedupe, new vs material change, delivery log, retry | E85: Not built | F85: Absent | G85: Build | H85: None | I85: No | J85: No | K85: No | L85: No | M85: No | O85: Phase 4 - Commercial launch
A86: AL-04 | B86: 8 | C86: P1 Partner | D86: Retention workflows (weekly digest, day-14, day-60, renewal) | E86: Not built | F86: Absent | G86: Build after AL-02 | H86: None | I86: No | J86: No | K86: No | L86: No | M86: No | N86: Consent rules | O86: Phase 6 - Partner growth
A87: PT-01 | B87: 9.1 | C87: P1 Partner | D87: Partner application, agreement, code/link, 30-day attribution | E87: Not built | F87: Absent | G87: Full build | H87: None | I87: No | J87: No | K87: No | L87: No | M87: No | N87: Commission rulebook | O87: Phase 6 - Partner growth
A88: PT-02 | B88: 9.2 | C88: P1 Partner | D88: Commission engine: tiers, clawback, payout statements | E88: Not built | F88: Absent | G88: Full build | H88: None | I88: No | J88: No | K88: No | L88: No | M88: No | N88: One approved schedule + CA | O88: Phase 6 - Partner growth
A89: PT-03 | B89: 9.3 | C89: P1 Partner | D89: Partner dashboard + exports (AT-14) | E89: Not built | F89: Absent | G89: Full build | H89: None | I89: No | J89: No | K89: No | L89: No | M89: No | O89: Phase 6 - Partner growth
A90: TM-01 | B90: 9.4 | C90: P2 Pro | D90: Team seats, roles, shared shortlist, pipeline stages, notes, access log | E90: Not built | F90: Absent | G90: Full build | H90: None | I90: No | J90: No | K90: No | L90: No | M90: No | N90: Team scope | O90: Phase 7 - Pro suite & scale
A91: TM-02 | B91: 9.4 | C91: P2 Pro | D91: Firm logo / client card config with safe upload | E91: Not built | F91: Absent | G91: Build with CM-02 | H91: None | I91: No | J91: No | K91: No | L91: No | M91: No | O91: Phase 7 - Pro suite & scale
A92: MD-01 | B92: 10 | C92: P1 Intel | D92: Store type, origin, rights, review state per asset; placeholders (AT-16) | E92: Not verified | F92: Live: property type page counts sum to 8,919 vs 9,304 published; 385 uncategorised; 'Vehicles' category shows 0 | G92: Rights fields + public gating not confirmed | H92: None | I92: Not verified | J92: No | K92: Yes | L92: Yes | M92: Partial | N92: Media policy | O92: Phase 5 - Intelligence
A93: MD-02 | B93: 10 | C93: P0 Comm | D93: Document access by entitlement; expiring signed links | E93: Not built | F93: Absent | G93: Depends on AC-04 | H93: None | I93: No | J93: No | K93: No | L93: No | M93: No | O93: Phase 4 - Commercial launch
A94: MD-03 | B94: 10 | C94: P1 Intel | D94: Admin content: guides, FAQs, city pages, Auction of the Day, video | E94: Partial | F94: Admin blog, pages, home config | G94: Auction of the Day, video, language variants absent | H94: None | I94: Partial | J94: No | K94: Yes | L94: Yes | M94: Not verified | O94: Phase 5 - Intelligence
A95: SE-01 | B95: 11 | C95: P0 Core | D95: Canonical URLs, metadata, sitemap, robots, pagination policy (AT-18) | E95: Partial | F95: Live: robots.txt ok (blocks /admin, /api, /login, /my-alerts); sitemap 10,268 URLs (9,180 property, 930 city); canonical on detail ok; /properties?city=X canonicalises to /properties | G95: 930 city URLs include many tiny cities (thin-page risk, spec 4.6); pagination/indexation policy undocumented | H95: None | I95: Partial | J95: No | K95: Yes | L95: Yes | M95: Partial | O95: Phase 1 - Trust fixes (code only)
A96: SE-02 | B96: 11 | C96: P0 Core | D96: No fabricated structured data | E96: Not verified | F96: JsonLd.tsx exists | G96: Audit output fields | H96: None | I96: Not verified | J96: No | K96: Yes | L96: Yes | M96: No | O96: Phase 1 - Trust fixes (code only)
A97: LG-01 | B97: 11 | C97: P2 Scale | D97: Hindi + 7 regional languages; labelled translations | E97: Not built | F97: Absent | G97: i18n framework + content | H97: None | I97: No | J97: No | K97: No | L97: No | M97: No | N97: Launch languages | O97: Phase 7 - Pro suite & scale
A98: AN-01 | B98: 11 | C98: P0 Comm | D98: Consent-aware analytics, UTM, signup-to-paid funnel | E98: Not built | F98: No analytics code found | G98: Choose tool, consent banner | H98: None | I98: No | J98: No | K98: No | L98: No | M98: No | N98: Analytics tool | O98: Phase 4 - Commercial launch
A99: AD-01 | B99: 12 | C99: P0 Core | D99: Admin: sources, duplicates, coverage, history, users, leads, payments, media, settings | E99: Partial | F99: Admin pages exist in code; I could not log in to admin in my browser, so admin behaviour was NOT audited live | G99: No risk queue, partner queue, location backlog, support tickets | H99: None | I99: Partial | J99: No | K99: Yes | L99: Yes | M99: NOT VERIFIED | O99: Phase 2 - Data foundation
A100: AD-02 | B100: 12 | C100: P0 Core | D100: Data-quality dashboard: missing city/coords/dates/prices, undated, end<start, contradictions | E100: Partial | F100: engine/coverage, completeness.ts, coverage.ts | G100: Undated/end<start/coords not confirmed; unassigned city not shown | H100: coverage.test.ts, completeness.test.ts | I100: Partial | J100: Partial | K100: Yes | L100: Yes | M100: Not verified | O100: Phase 2 - Data foundation
...

Sheet Acceptance tests
A1: ID | B1: Test | C1: Status | D1: Evidence | E1: Implemented | F1: Tested | G1: Merged | H1: Deployed | I1: Prod smoke-tested
A2: AT-01 | B2: City count parity | C2: Partial | D2: Parity holds (8/8 tiles) but on canonical-city rows only; ~56% of catalogue has no canonical city | E2: Yes | F2: Yes | G2: Yes | H2: Yes | I2: Yes
A3: AT-02 | B3: Lifecycle | C3: Partial | D3: Active/Live/Today/Completed/Cancelled/Postponed tested; Undated state absent | E3: Yes | F3: Yes | G3: Yes | H3: Yes | I3: NV
A4: AT-03 | B4: Distinct property count | C4: Done | D4: Property-level counts; unit-tested | E4: Yes | F4: Yes | G4: Yes | H4: Yes | I4: Partial
A5: AT-04 | B5: No auction round | C5: Done | D5: Catalogue vs active definitions | E5: Yes | F5: Yes | G5: Yes | H5: Yes | I5: Partial
A6: AT-05 | B6: Unknown city | C6: Partial | D6: Not assigned by fuzzy match (good) but bucket never reported; live gap ~5,236 properties | E6: Yes | F6: Yes | G6: Yes | H6: Yes | I6: FAIL (invisible gap)
A7: AT-06 | B7: Map/list parity | C7: Partial | D7: Filter parity unit-tested; production has no coordinates so pins untested live | E7: Yes | F7: Yes | G7: Yes | H7: Yes | I7: FAIL (0 pins)
A8: AT-07 | B8: Pagination | C8: Partial | D8: /properties paginates; /auctions/* capped at 48 with no pager, page 2 repeats page 1; no sort | E8: Partial | F8: Partial | G8: Yes | H8: Yes | I8: FAIL (/auctions)
A9: AT-08 | B9: Premium access | C9: Not built | D9: No entitlements | E9: No | F9: No | G9: No | H9: No | I9: No
A10: AT-09 | B10: Payment integrity | C10: Not built | D10: No webhook/checkout found | E10: No | F10: No | G10: No | H10: No | I10: No
A11: AT-10 | B11: Renewal/refund | C11: Not built | E11: No | F11: No | G11: No | H11: No | I11: No
A12: AT-11 | B12: Alerts | C12: Not built | D12: Alert records only; no delivery | E12: No | F12: No | G12: No | H12: No | I12: No
A13: AT-12 | B13: Risk provenance | C13: Not built | D13: No risk flags | E13: No | F13: No | G13: No | H13: No | I13: No
A14: AT-13 | B14: Source controls | C14: Partial | D14: Robots/HTTP-status tests exist; per-source audit not redone | E14: Yes | F14: Unit tests exist | G14: Yes | H14: Yes | I14: NV
A15: AT-14 | B15: Partner attribution | C15: Not built | E15: No | F15: No | G15: No | H15: No | I15: No
A16: AT-15 | B16: Client report | C16: Not built | E16: No | F16: No | G16: No | H16: No | I16: No
A17: AT-16 | B17: Media rights | C17: Not verified | D17: Models exist; gating not checked | E17: NV | F17: No | G17: Yes | H17: Yes | I17: No
A18: AT-17 | B18: Privacy/security | C18: Partial | D18: Borrower-data test only | E18: Partial | F18: Partial | G18: Yes | H18: Yes | I18: No
A19: AT-18 | B19: SEO | C19: Partial | D19: Sitemap/robots/canonicals exist; not audited | E19: Partial | F19: No | G19: Yes | H19: Yes | I19: NV
A20: AT-19 | B20: Support and correction | C20: Partial | D20: Contact form only | E20: Partial | F20: No | G20: Yes | H20: Yes | I20: NV
A21: AT-20 | B21: Production smoke test | C21: Partial | D21: Done this session for homepage tiles, search, city, map toggle only. Not done: detail, sign-in, pricing, payment, alerts, admin | E21: Partial | F21: n/a | G21: n/a | H21: Yes | I21: Partial

Sheet Owner decisions
A1: Decision | B1: Spec § | C1: Current state | D1: What it blocks | E1: Needed by
A2: Final plan prices and GST display | B2: 7.3 | C2: Not decided | D2: Blocks checkout, pricing page, partner creatives | E2: Phase 0 - Decide & baseline
A3: Free-tier delay and masking | B3: 7.2 | C3: Not decided | D3: Blocks entitlement layer (AT-08) | E3: Phase 0 - Decide & baseline
A4: Refund policy | B4: 7.4 | C4: Not decided | D4: Blocks refund flow, checkout copy | E4: Phase 0 - Decide & baseline
A5: Map provider | B5: 4.5 | C5: Using free OSM tiles | D5: Confirm acceptable for launch traffic or pick paid provider | E5: Phase 0 - Decide & baseline
A6: Risk rubric | B6: 5.2 | C6: Not decided | D6: Blocks risk flags (P1) | E6: Phase 5 - Intelligence
A7: Source permissions | B7: 6 | C7: Not decided | D7: Blocks any new source | E7: Phase 0 - Decide & baseline
A8: Media permissions | B8: 10 | C8: Not decided | D8: Blocks gallery, thumbnails, AT-16 | E8: Phase 0 - Decide & baseline
A9: Language launch waves | B9: 11 | C9: Not decided | D9: Blocks i18n | E9: Phase 7 - Pro suite & scale
A10: MMR membership list | B10: 4.6 | C10: Draft only | D10: Blocks MMR view | E10: Phase 0 - Decide & baseline
A11: Partner commission schedule | B11: 9.2 | C11: Multiple proposals | D11: Blocks partner build | E11: Phase 6 - Partner growth
A12: Team and Private Desk scope | B12: 9.4 | C12: Not decided | D12: Blocks P2 suite | E12: Phase 7 - Pro suite & scale
... A18: Coordinates for properties | B18: 4.5 | C18: New - from live check | D18: Map has 0 pins; needs owner-approved data task (no invented coordinates) | E18: Phase 0 - Decide & baseline
